Metadata-Version: 2.4
Name: streamlit-free-text-select
Version: 0.3.0
Summary: A Streamlit component that allows you to select from a list of options or enter a custom value.
Home-page: 
Author: Sander Hummerich
Author-email: sander.hummerich@gmx.de
Requires-Python: >=3.7
Requires-Dist: streamlit>=0.63
Provides-Extra: devel
Requires-Dist: wheel; extra == "devel"
Requires-Dist: pytest==7.4.0; extra == "devel"
Requires-Dist: playwright==1.39.0; extra == "devel"
Requires-Dist: requests==2.31.0; extra == "devel"
Requires-Dist: pytest-playwright-snapshot==1.0; extra == "devel"
Requires-Dist: pytest-rerunfailures==12.0; extra == "devel"
Dynamic: author
Dynamic: author-email
Dynamic: description
Dynamic: description-content-type
Dynamic: provides-extra
Dynamic: requires-dist
Dynamic: requires-python
Dynamic: summary
